<?xml version="1.0" encoding="utf-8"?>
<base xmlns:xsi="http://www.w3.org/2001/XMLSchema-instance" xmlns:xsd="http://www.w3.org/2001/XMLSchema" type="string">
  <tags>
    <tag language="Русский"/>
  </tags>
  <strings>
	
	<!-- Mod name -->
	<string id="Telepathy_Mod_Name" text="Телепатия Мод"/>

	<!-- Interface -->
	<string id="Telepathy_Talk_To_Me" text="Поговори со мной!"/>
	<string id="Telepathy_Hero_Will_Talk" text="{HeroName} скоро поговорит с вами..."/>

	<!-- Dialog -->
	<string id="Telepathy_Ask_Something" text="Хочу кое-что спросить..."/>
	<string id="Telepathy_What_Is_It" text="О чём?"/>
	<string id="Telepathy_Where_Are_You" text="Где ты находишься?"/>
	<string id="Telepathy_Im_In" text="Я в {Settlement}."/>
	<string id="Telepathy_Im_Near" text="Я недалеко от {Settlement}."/>
	<string id="Telepathy_What_Are_You_Doing" text="Чем ты занимаешься?"/>
	<string id="Telepathy_Nothing" text="Ничем."/>
	<string id="Telepathy_NotYourBusiness" text="Не твоё дело!"/>
	
	<!-- Settings -->
	<string id="Telepathy_Settings_100" text="Реализм дистанционного общения"/>
	<string id="Telepathy_Settings_110" text="Запретить разговоры с мертвыми"/>
	<string id="Telepathy_Settings_111" text="Дистанционное общение с мертвыми героями невозможно."/>
	<string id="Telepathy_Settings_120" text="Режим голубиной почты"/>
	<string id="Telepathy_Settings_121" text="Доставка сообщений займет некоторое время, зависящее от расстояния до героя, с которым вы собираетесь поговорить."/>
	<string id="Telepathy_Settings_130" text="Запретить разговоры с незнакомыми героями"/>
	<string id="Telepathy_Settings_131" text="Дистанционное общение с героями, которых главный герой не встречал прежде, невозможно."/>
	<string id="Telepathy_Settings_140" text="Скрыть квестовые реплики диалогов"/>
	<string id="Telepathy_Settings_141" text="Скрыть квестовые реплики диалогов во время дистанционного общения."/>

  </strings>
</base>